odoo10_addon_mass_sorting-10.0.1.0.0.99.dev16-py3.8-nspkg.pth
odoo/addons/mass_sorting/README.rst
odoo/addons/mass_sorting/__init__.py
odoo/addons/mass_sorting/__manifest__.py
odoo/addons/mass_sorting/demo/function.xml
odoo/addons/mass_sorting/demo/mass_sort_config.xml
odoo/addons/mass_sorting/demo/mass_sort_config_line.xml
odoo/addons/mass_sorting/i18n/am.po
odoo/addons/mass_sorting/i18n/ar.po
odoo/addons/mass_sorting/i18n/bg.po
odoo/addons/mass_sorting/i18n/bs.po
odoo/addons/mass_sorting/i18n/ca.po
odoo/addons/mass_sorting/i18n/ca_ES.po
odoo/addons/mass_sorting/i18n/cs.po
odoo/addons/mass_sorting/i18n/da.po
odoo/addons/mass_sorting/i18n/de.po
odoo/addons/mass_sorting/i18n/el_GR.po
odoo/addons/mass_sorting/i18n/en_AU.po
odoo/addons/mass_sorting/i18n/en_GB.po
odoo/addons/mass_sorting/i18n/es.po
odoo/addons/mass_sorting/i18n/es_AR.po
odoo/addons/mass_sorting/i18n/es_CL.po
odoo/addons/mass_sorting/i18n/es_CO.po
odoo/addons/mass_sorting/i18n/es_CR.po
odoo/addons/mass_sorting/i18n/es_DO.po
odoo/addons/mass_sorting/i18n/es_EC.po
odoo/addons/mass_sorting/i18n/es_ES.po
odoo/addons/mass_sorting/i18n/es_MX.po
odoo/addons/mass_sorting/i18n/es_PE.po
odoo/addons/mass_sorting/i18n/es_PY.po
odoo/addons/mass_sorting/i18n/es_VE.po
odoo/addons/mass_sorting/i18n/et.po
odoo/addons/mass_sorting/i18n/eu.po
odoo/addons/mass_sorting/i18n/fa.po
odoo/addons/mass_sorting/i18n/fi.po
odoo/addons/mass_sorting/i18n/fr.po
odoo/addons/mass_sorting/i18n/fr_CA.po
odoo/addons/mass_sorting/i18n/fr_CH.po
odoo/addons/mass_sorting/i18n/fr_FR.po
odoo/addons/mass_sorting/i18n/gl.po
odoo/addons/mass_sorting/i18n/gl_ES.po
odoo/addons/mass_sorting/i18n/he.po
odoo/addons/mass_sorting/i18n/hi.po
odoo/addons/mass_sorting/i18n/hr.po
odoo/addons/mass_sorting/i18n/hr_HR.po
odoo/addons/mass_sorting/i18n/hu.po
odoo/addons/mass_sorting/i18n/id.po
odoo/addons/mass_sorting/i18n/it.po
odoo/addons/mass_sorting/i18n/ja.po
odoo/addons/mass_sorting/i18n/ko.po
odoo/addons/mass_sorting/i18n/lo.po
odoo10_addon_mass_sorting-10.0.1.0.0.99.dev16.dist-info/METADATA
odoo10_addon_mass_sorting-10.0.1.0.0.99.dev16.dist-info/WHEEL
odoo10_addon_mass_sorting-10.0.1.0.0.99.dev16.dist-info/namespace_packages.txt
odoo10_addon_mass_sorting-10.0.1.0.0.99.dev16.dist-info/top_level.txt
odoo10_addon_mass_sorting-10.0.1.0.0.99.dev16.dist-info/RECORD
